{
    "info": [
        {
            "id": -1002162071088,
            "phrases": [
                "1488 паритет пасхалко",
                "кчау",
                "мы такое любим",
                "ты пидор",
                "плаке плаке или щовель?",
                "кринж, я ливаю",
                "сверху гей",
                "чушпанам слова не давали",
                "симпампусик",
                "сядь мне на лицо",
                "привет спампусик🥰🥰🥰",
                "топ пикча",
                "красивое",
                "писькализычи вперед",
                "имбо скинь еще",
                "монтик одобряет",
                "спасибочки за то что я такой охуенный",
                "я добрый но если надо 😮‍💨💨🍆💦🇺🇸",
                "ухх... ты такой сладкий🥵🥵😘☠️🥵🥶🥶🤏🤏😐😣😣😄😐",
                "глотайте член",
                "падари стикерпак",
                "Писда наху",
                "☠️",
                "хахахахахахахах",
                "какие у тебя трусики?",
                "дай помацать сисю",
                "69 монтик тайно дернул",
                "Иван золо2004 гений",
                "🥶🥶🥶🥶🥶🥶🥶🥶🥶🥶🥶🥶🥶",
                "у меня траур",
                "сверху геи"
            ]
        },
        {
            "id": -4276733091,
            "phrases": []
        },
        {
            "id": 1856059939,
            "phrases": [
                "13"
            ]
        },
        {
            "id": 7142831455,
            "phrases": []
        },
        {
            "id": 2025251523,
            "phrases": []
        },
        {
            "id": 5424794687,
            "phrases": [
                "ты кто"
            ]
        }
    ]
}